setup.py
Smart_Solver.egg-info/PKG-INFO
Smart_Solver.egg-info/SOURCES.txt
Smart_Solver.egg-info/dependency_links.txt
Smart_Solver.egg-info/requires.txt
Smart_Solver.egg-info/top_level.txt
Smart_Solver/searches/__init__.py
Smart_Solver/searches/advertisal.py
Smart_Solver/searches/informed.py
Smart_Solver/searches/local.py
Smart_Solver/searches/uninformed.py
Smart_Solver/utile/__init__.py
Smart_Solver/utile/problem.py
Smart_Solver/utile/util.py