Metadata-Version: 2.1
Name: Smart-Solver
Version: 1.0
Summary: Smart Solver for games with AI search Algorithms
License: UNKNOWN
Platform: UNKNOWN
